diceseq/__init__.py
diceseq/bias_estimate.py
diceseq/bias_merge.py
diceseq/bias_plot.py
diceseq/dice_count.py
diceseq/dice_test.py
diceseq/diceseq.py
diceseq/diceseq_static.py
diceseq/gtf_test.py
diceseq/gtf_utils_old.py
diceseq/read_simulate.py
diceseq/tran_utils.py
diceseq/models/__init__.py
diceseq/models/model_dynamic.py
diceseq/models/model_GP.py
diceseq/models/model_static.py
diceseq/utils/__init__.py
diceseq/utils/bias_utils.py
diceseq/utils/gtf_utils.py
diceseq/utils/reads_utils.py
diceseq/utils/sam_utils.py
diceseq/utils/tran_utils.py
diceseq-0.0.1.dist-info/DESCRIPTION.rst
diceseq-0.0.1.dist-info/entry_points.txt
diceseq-0.0.1.dist-info/METADATA
diceseq-0.0.1.dist-info/metadata.json
diceseq-0.0.1.dist-info/RECORD
diceseq-0.0.1.dist-info/top_level.txt
diceseq-0.0.1.dist-info/WHEEL
