Metadata-Version: 2.0
Name: diceseq
Version: 0.0.1
Summary: DICEseq
Home-page: http://diceseq.sourceforge.net
Author: Yuanhua Huang
Author-email: Y.Huang@ed.ac.uk
License: MIT
Keywords: RNA splicing,RNA-seq,dynamics,probabilistic models
Platform: UNKNOWN
Requires-Dist: numpy
Requires-Dist: scipy
Requires-Dist: matplotlib
Requires-Dist: h5py
Requires-Dist: pysam
